setup.py
probability_distributions_v1_0_mlnd/Binomialdistribution.py
probability_distributions_v1_0_mlnd/Gaussiandistribution.py
probability_distributions_v1_0_mlnd/Generaldistribution.py
probability_distributions_v1_0_mlnd/__init__.py
probability_distributions_v1_0_mlnd.egg-info/PKG-INFO
probability_distributions_v1_0_mlnd.egg-info/SOURCES.txt
probability_distributions_v1_0_mlnd.egg-info/dependency_links.txt
probability_distributions_v1_0_mlnd.egg-info/not-zip-safe
probability_distributions_v1_0_mlnd.egg-info/top_level.txt