Metadata-Version: 1.0
Name: probability-distributions-v1-0-mlnd
Version: 1.0
Summary: Gaussian and Binomial distributions
Home-page: UNKNOWN
Author: Megha Rana
Author-email: megha14492@gmail.com
License: UNKNOWN
Platform: UNKNOWN
